odoo/addons/ssi_data_requirement_google_drive/README.rst
odoo/addons/ssi_data_requirement_google_drive/__init__.py
odoo/addons/ssi_data_requirement_google_drive/__manifest__.py
odoo/addons/ssi_data_requirement_google_drive/models/__init__.py
odoo/addons/ssi_data_requirement_google_drive/models/data_requirement.py
odoo/addons/ssi_data_requirement_google_drive/models/data_requirement_type.py
odoo/addons/ssi_data_requirement_google_drive/static/description/icon.png
odoo/addons/ssi_data_requirement_google_drive/views/data_requirement_type_views.xml
odoo/addons/ssi_data_requirement_google_drive/views/data_requirement_views.xml
odoo14_addon_ssi_data_requirement_google_drive-14.0.1.1.0.dist-info/METADATA
odoo14_addon_ssi_data_requirement_google_drive-14.0.1.1.0.dist-info/WHEEL
odoo14_addon_ssi_data_requirement_google_drive-14.0.1.1.0.dist-info/top_level.txt
odoo14_addon_ssi_data_requirement_google_drive-14.0.1.1.0.dist-info/RECORD
